README.txt
setup.py
docs/Developers.txt
docs/HISTORY.txt
wm/__init__.py
wm.gloeggele.egg-info/PKG-INFO
wm.gloeggele.egg-info/SOURCES.txt
wm.gloeggele.egg-info/dependency_links.txt
wm.gloeggele.egg-info/entry_points.txt
wm.gloeggele.egg-info/namespace_packages.txt
wm.gloeggele.egg-info/requires.txt
wm.gloeggele.egg-info/top_level.txt
wm.gloeggele.egg-info/zip-safe
wm/gloeggele/__init__.py
wm/gloeggele/menu.py