Metadata-Version: 1.0
Name: wm.gloeggele
Version: 1.2
Summary: Commandline parser for the online-menu of http://www.gloeggele.com
Home-page: https://svn.webmeisterei.com/repos/public/wm.gloeggele
Author: Harald Friessnegger
Author-email: harald at webmeisterei (dot) com
License: GPL
Keywords: xml fun gloeggele
Platform: UNKNOWN
Classifier: Programming Language :: Python :: 2.5
Classifier: Environment :: Console
Classifier: Operating System :: OS Independent
Classifier: Development Status :: 5 - Production/Stable
Classifier: Topic :: Utilities
